chase/__init__.py
chase/account.py
chase/order.py
chase/session.py
chase/symbols.py
chase/urls.py
chaseinvest_api-0.4.7.dist-info/licenses/LICENSE
chaseinvest_api-0.4.7.dist-info/METADATA
chaseinvest_api-0.4.7.dist-info/WHEEL
chaseinvest_api-0.4.7.dist-info/top_level.txt
chaseinvest_api-0.4.7.dist-info/RECORD
