Metadata-Version: 2.4
Name: chaseinvest-api
Version: 0.4.7
Summary: An unofficial API for Chase Invest.
Author: MaxxRK
License-Expression: MIT
Keywords: CHASE,API
Classifier: Development Status :: 3 - Alpha
Classifier: Intended Audience :: Developers
Classifier: Topic :: Internet :: WWW/HTTP :: Session
Classifier: Programming Language :: Python :: 3.12
Classifier: Programming Language :: Python :: 3.13
Classifier: Programming Language :: Python :: 3.14
Requires-Python: >=3.12
License-File: LICENSE
Requires-Dist: zendriver
Requires-Dist: anyio
Requires-Dist: curl-cffi
Dynamic: license-file
